kaspian/__init__.py
kaspian/api.py
kaspian-0.0.1.dist-info/METADATA
kaspian-0.0.1.dist-info/WHEEL
kaspian-0.0.1.dist-info/licenses/LICENSE
kaspian-0.0.1.dist-info/RECORD
